mealy_design.sv
`timescale 1ns/1ps

module state_machine_mealy #(parameter SEQ = 2'b11) (input clk, reset, in, output reg out);
    parameter IDLE = 2'b00, ONE = 2'b01, DETECT = 2'b10;

    reg [1:0] state, next_state;

    // State Transition Logic
    always @(posedge clk or posedge reset) begin
        if (reset)
            state <= IDLE;
        else
            state <= next_state;
    end

    // Next State Logic
    always @(*) begin
        case (state)
            IDLE: begin
                if (in == SEQ[1])
                    next_state = ONE;
                else
                    next_state = IDLE;
            end
            ONE: begin
                if (in == SEQ[0])
                    next_state = DETECT;
                else if (in == SEQ[1])
                    next_state = ONE; // Remain in ONE for consecutive 1s
                else
                    next_state = IDLE;
            end
            DETECT: begin
                if (in == SEQ[1])
                    next_state = ONE;
                else
                    next_state = IDLE;
            end
            default: next_state = IDLE;
        endcase
    end

    // Output Logic
    always @(state) begin
        case (state)
            IDLE: out = 0;
            ONE: out = 0;
            DETECT: out = 1; // Sequence detected
            default: out = 0;
        endcase
    end
endmodule

mealy_testbench.sv
`timescale 1ns/1ps

module state_machine_mealy_tb();
    reg clk, reset, in;
    wire out;

    // Instantiate the DUT
    state_machine_mealy #(2'b11) dut(.clk(clk), .reset(reset), .in(in), .out(out));

    // Clock Generation
    initial begin
        clk = 0;
        forever #5 clk = ~clk; // Generate clock with period of 10ns
    end

    // Test Sequence
    initial begin
        $dumpfile("mealy_waveform.vcd");
        $dumpvars(0, state_machine_mealy_tb);

        // Reset and Initialize
        reset = 1;
        in = 0;
        #10 reset = 0;

        // Sequence Testing
        #10 in = 1;
        #10 in = 1; // Sequence 11 detected
        #10 in = 0;
        #10 in = 1;
        #10 in = 1; // Sequence 11 detected
        #10 in = 0;

        // Additional Random Input
        #20 in = 1;
        #10 in = 1; // Sequence 11 detected
        #10 in = 0;
        #20;

        $finish;
    end
endmodule

mealy_waveform.vcd
$date
	Tue Dec  3 01:24:31 2024
$end
$version
	Icarus Verilog
$end
$timescale
	1ps
$end
$scope module state_machine_mealy_tb $end
$var wire 1 ! out $end
$var reg 1 " clk $end
$var reg 1 # in $end
$var reg 1 $ reset $end
$scope module dut $end
$var wire 1 " clk $end
$var wire 1 # in $end
$var wire 1 $ reset $end
$var parameter 2 % DETECT $end
$var parameter 2 & IDLE $end
$var parameter 2 ' ONE $end
$var parameter 2 ( SEQ $end
$var reg 2 ) next_state [1:0] $end
$var reg 1 ! out $end
$var reg 2 * state [1:0] $end
$upscope $end
$upscope $end
$enddefinitions $end
$comment Show the parameter values. $end
$dumpall
b11 (
b1 '
b0 &
b10 %
$end
#0
$dumpvars
b0 *
b0 )
1$
0#
0"
0!
$end
#5000
1"
#10000
0"
0$
#15000
1"
#20000
b1 )
0"
1#
#25000
b10 )
b1 *
1"
#30000
0"
#35000
1!
b1 )
b10 *
1"
#40000
b0 )
0"
0#
#45000
0!
b0 *
1"
#50000
b1 )
0"
1#
#55000
b10 )
b1 *
1"
#60000
0"
#65000
1!
b1 )
b10 *
1"
#70000
b0 )
0"
0#
#75000
0!
b0 *
1"
#80000
0"
#85000
1"
#90000
b1 )
0"
1#
#95000
b10 )
b1 *
1"
#100000
0"
#105000
1!
b1 )
b10 *
1"
#110000
b0 )
0"
0#
#115000
0!
b0 *
1"
