moore_design.sv
// Advanced Moore State Machine
module moore_sequence_detector #(parameter SIZE = 4) (
    input clk,
    input reset,
    input in,
    output reg out
);
    // State encoding using parameters
    parameter S0 = 3'b000, S1 = 3'b001, S2 = 3'b010, S3 = 3'b011, S4 = 3'b100;
    reg [2:0] state, next_state;

    // Sequential logic for state transition
    always @(posedge clk or posedge reset) begin
        if (reset)
            state <= S0;
        else
            state <= next_state;
    end

    // Combinational logic for next state and output
    always @(*) begin
        // Default assignments
        next_state = S0;
        out = 0;

        case (state)
            S0: if (in) next_state = S1; else next_state = S0;
            S1: if (!in) next_state = S2; else next_state = S1;
            S2: if (in) next_state = S3; else next_state = S0;
            S3: if (in) next_state = S4; else next_state = S2;
            S4: begin
                out = 1; // Sequence detected
                if (!in) next_state = S2; else next_state = S4;
            end
            default: next_state = S0; // Error recovery
        endcase
    end
endmodule

moore_testbench.sv
`timescale 1ns/1ps

module moore_sequence_detector_tb();
    reg clk, reset, in;
    wire out;

    // Instantiate the DUT
    moore_sequence_detector dut(
        .clk(clk),
        .reset(reset),
        .in(in),
        .out(out)
    );

    // Clock generation
    initial begin
        clk = 0;
        forever #5 clk = ~clk; // 10 ns clock period
    end

    // Test sequence
    initial begin
        $dumpfile("moore_waveform.vcd"); // VCD output
        $dumpvars(0, moore_sequence_detector_tb);

        reset = 1; in = 0;
        #12 reset = 0;

        // Input sequence: 1011
        #10 in = 1;
        #10 in = 0;
        #10 in = 1;
        #10 in = 1; // Sequence "1011" detected
        #10 in = 0;
        #10 in = 1;
        #10 in = 0;
        #10 in = 1; // Random inputs

        #50 $finish;
    end
endmodule

moore_waveform.vcd
$date
	Tue Dec  3 01:45:36 2024
$end
$version
	Icarus Verilog
$end
$timescale
	1ps
$end
$scope module moore_sequence_detector_tb $end
$var wire 1 ! out $end
$var reg 1 " clk $end
$var reg 1 # in $end
$var reg 1 $ reset $end
$scope module dut $end
$var wire 1 " clk $end
$var wire 1 # in $end
$var wire 1 $ reset $end
$var parameter 3 % S0 $end
$var parameter 3 & S1 $end
$var parameter 3 ' S2 $end
$var parameter 3 ( S3 $end
$var parameter 3 ) S4 $end
$var parameter 32 * SIZE $end
$var reg 3 + next_state [2:0] $end
$var reg 1 ! out $end
$var reg 3 , state [2:0] $end
$upscope $end
$upscope $end
$enddefinitions $end
$comment Show the parameter values. $end
$dumpall
b100 *
b100 )
b11 (
b10 '
b1 &
b0 %
$end
#0
$dumpvars
b0 ,
b0 +
1$
0#
0"
0!
$end
#5000
1"
#10000
0"
#12000
0$
#15000
1"
#20000
0"
#22000
b1 +
1#
#25000
b1 +
b1 ,
1"
#30000
0"
#32000
b10 +
0#
#35000
b0 +
b10 ,
1"
#40000
0"
#42000
b11 +
1#
#45000
b100 +
b11 ,
1"
#50000
0"
#55000
1!
b100 +
b100 ,
1"
#60000
0"
#62000
1!
b10 +
0#
#65000
0!
b0 +
b10 ,
1"
#70000
0"
#72000
b11 +
1#
#75000
b100 +
b11 ,
1"
#80000
0"
#82000
b10 +
0#
#85000
b0 +
b10 ,
1"
#90000
0"
#92000
b11 +
1#
#95000
b100 +
b11 ,
1"
#100000
0"
#105000
1!
b100 +
b100 ,
1"
